eox_tenant/__init__.py
eox_tenant/admin.py
eox_tenant/apps.py
eox_tenant/async_utils.py
eox_tenant/auth.py
eox_tenant/constants.py
eox_tenant/middleware.py
eox_tenant/models.py
eox_tenant/organizations.py
eox_tenant/permissions.py
eox_tenant/pipeline.py
eox_tenant/receivers_helpers.py
eox_tenant/signals.py
eox_tenant/test_utils.py
eox_tenant/urls.py
eox_tenant/utils.py
eox_tenant/validators.py
eox_tenant/views.py
eox_tenant/widgets.py
eox_tenant/api/__init__.py
eox_tenant/api/urls.py
eox_tenant/api/v1/__init__.py
eox_tenant/api/v1/permissions.py
eox_tenant/api/v1/routers.py
eox_tenant/api/v1/serializers.py
eox_tenant/api/v1/urls.py
eox_tenant/api/v1/viewsets.py
eox_tenant/api/v1/tests/__init__.py
eox_tenant/api/v1/tests/test_microsites.py
eox_tenant/api/v1/tests/test_permissions.py
eox_tenant/api/v1/tests/test_routes.py
eox_tenant/api/v1/tests/test_tenant_config.py
eox_tenant/edxapp_wrapper/__init__.py
eox_tenant/edxapp_wrapper/auth.py
eox_tenant/edxapp_wrapper/bearer_authentication.py
eox_tenant/edxapp_wrapper/branding_api.py
eox_tenant/edxapp_wrapper/edxmako_module.py
eox_tenant/edxapp_wrapper/get_common_util.py
eox_tenant/edxapp_wrapper/oauth_dispatch.py
eox_tenant/edxapp_wrapper/site_configuration_module.py
eox_tenant/edxapp_wrapper/theming_helpers.py
eox_tenant/edxapp_wrapper/users.py
eox_tenant/edxapp_wrapper/backends/__init__.py
eox_tenant/edxapp_wrapper/backends/bearer_authentication_l_v1.py
eox_tenant/edxapp_wrapper/backends/bearer_authentication_test_v1.py
eox_tenant/edxapp_wrapper/backends/branding_api_l_v1.py
eox_tenant/edxapp_wrapper/backends/edx_auth_n_v1.py
eox_tenant/edxapp_wrapper/backends/edxmako_l_v1.py
eox_tenant/edxapp_wrapper/backends/oauth_dispatch_j_v1.py
eox_tenant/edxapp_wrapper/backends/site_configuration_module_i_v1.py
eox_tenant/edxapp_wrapper/backends/site_configuration_module_test_v1.py
eox_tenant/edxapp_wrapper/backends/theming_helpers_h_v1.py
eox_tenant/edxapp_wrapper/backends/theming_helpers_test_v1.py
eox_tenant-14.2.1.dist-info/licenses/LICENSE.txt
eox_tenant-14.2.1.dist-info/METADATA
eox_tenant-14.2.1.dist-info/WHEEL
eox_tenant-14.2.1.dist-info/entry_points.txt
eox_tenant-14.2.1.dist-info/top_level.txt
eox_tenant-14.2.1.dist-info/RECORD
