Metadata-Version: 2.4
Name: eox-tenant
Version: 14.2.1
Summary: Edunext Open edx extensions tenant.
Author: eduNEXT
Author-email: contact@edunext.co
License: AGPL
Classifier: Development Status :: 5 - Production/Stable
Classifier: Framework :: Django :: 4.2
Classifier: Framework :: Django :: 5.2
Classifier: Intended Audience :: Developers
Classifier: License :: OSI Approved :: GNU Affero General Public License v3
Classifier: Operating System :: OS Independent
Classifier: Programming Language :: Python :: 3.11
Classifier: Programming Language :: Python :: 3.12
License-File: LICENSE.txt
Dynamic: author
Dynamic: author-email
Dynamic: classifier
Dynamic: description
Dynamic: description-content-type
Dynamic: license
Dynamic: license-file
Dynamic: summary
